yices_api.py
test/__init__.py
test/context_test.py
test/delegate_test.py
test/dimacs_test.py
test/error_test.py
test/interpolationcontext_test.py
test/model_test.py
test/terms_test.py
test/types_test.py
test/utils.py
test_api/__init__.py
test_api/context_test.py
test_api/error_test.py
test_api/model_test.py
test_api/terms_test.py
test_api/types_test.py
test_api/vector_test.py
yices/Census.py
yices/Config.py
yices/Constructors.py
yices/Context.py
yices/Delegates.py
yices/Dimacs.py
yices/InterpolationContext.py
yices/Model.py
yices/Parameters.py
yices/Profiler.py
yices/Status.py
yices/StringBuilder.py
yices/Terms.py
yices/Types.py
yices/Yices.py
yices/YicesException.py
yices/Yvals.py
yices/__init__.py
yices-1.1.6.dist-info/LICENSE
yices-1.1.6.dist-info/METADATA
yices-1.1.6.dist-info/WHEEL
yices-1.1.6.dist-info/entry_points.txt
yices-1.1.6.dist-info/top_level.txt
yices-1.1.6.dist-info/RECORD
